setup.py
Flight/__init__.py
Flight/dustparticle.py
Flight/pilot.py
Flight/polygon.py
Flight/spaceObject.py
Flight.egg-info/PKG-INFO
Flight.egg-info/SOURCES.txt
Flight.egg-info/dependency_links.txt
Flight.egg-info/entry_points.txt
Flight.egg-info/requires.txt
Flight.egg-info/top_level.txt