Metadata-Version: 1.0
Name: Flight
Version: 0.9
Summary: This is building towards a flight simulation
Home-page: UNKNOWN
Author: William Coleman
Author-email: weecol@unlimitedmail.org
License: PSF
Platform: UNKNOWN
